cuwais/__init__.py
cuwais/common.py
cuwais/config.py
cuwais/database.py
cuwais/gamemodes.py
cuwais_common-1.3.1.dist-info/LICENSE
cuwais_common-1.3.1.dist-info/METADATA
cuwais_common-1.3.1.dist-info/WHEEL
cuwais_common-1.3.1.dist-info/top_level.txt
cuwais_common-1.3.1.dist-info/RECORD
