Metadata-Version: 2.1
Name: cuwais-common
Version: 1.3.1
Summary: The shared libraries for CUWAIS competitions
Home-page: https://github.com/AI-Wars-Soc/common
Author: Joe O'Connor
Author-email: jo429@cam.ac.uk
License: UNKNOWN
Platform: UNKNOWN
Classifier: Programming Language :: Python :: 3
Classifier: License :: OSI Approved :: MIT License
Classifier: Operating System :: OS Independent
Requires-Python: >=3.6
License-File: LICENSE
Requires-Dist: sqlalchemy (~=1.4.23)
Requires-Dist: pyyaml (~=5.4.1)
Requires-Dist: psycopg2 (~=2.9.1)
Requires-Dist: chess (~=1.6.1)
